{
    "like_max": 524,
    "id": 227653085,
    "index": 7949,
    "title": "讀了四年的成大"
}{
    "like_max": 357,
    "id": 227928001,
    "index": 6521,
    "title": "給愛心"
}{
    "like_max": 353,
    "id": 227785525,
    "index": 7309,
    "title": "南台一日遊"
}{
    "like_max": 326,
    "id": 227832546,
    "index": 7005,
    "title": "新聞：女多於男，恐嫁不掉（內附截圖與殘酷真相）"
}{
    "like_max": 307,
    "id": 227346590,
    "index": 9379,
    "title": "做功德求畢業之成大學生空間整理"
}{
    "like_max": 295,
    "id": 227329018,
    "index": 9490,
    "title": "奧莉薇老闆娘喊破喉嚨，引眾人圍觀不捨"
}{
    "like_max": 294,
    "id": 229139492,
    "index": 1089,
    "title": "還在奮鬥的夥伴們"
}{
    "like_max": 281,
    "id": 228621070,
    "index": 3800,
    "title": "關於家境"
}{
    "like_max": 281,
    "id": 228223843,
    "index": 5260,
    "title": "[自薦課程] 人工智慧應用實務"
}{
    "like_max": 274,
    "id": 229140459,
    "index": 1081,
    "title": "互相幫助的成大"
}
文章網址: 
讀了四年的成大 : https://www.dcard.tw/f/ncku/p/227653085
給愛心 : https://www.dcard.tw/f/ncku/p/227928001
南台一日遊 : https://www.dcard.tw/f/ncku/p/227785525
新聞：女多於男，恐嫁不掉（內附截圖與殘酷真相） : https://www.dcard.tw/f/ncku/p/227832546
做功德求畢業之成大學生空間整理 : https://www.dcard.tw/f/ncku/p/227346590
奧莉薇老闆娘喊破喉嚨，引眾人圍觀不捨 : https://www.dcard.tw/f/ncku/p/227329018
還在奮鬥的夥伴們 : https://www.dcard.tw/f/ncku/p/229139492
關於家境 : https://www.dcard.tw/f/ncku/p/228621070
[自薦課程] 人工智慧應用實務 : https://www.dcard.tw/f/ncku/p/228223843
互相幫助的成大 : https://www.dcard.tw/f/ncku/p/229140459
